lmcloud/__init__.py
lmcloud/client_bluetooth.py
lmcloud/client_cloud.py
lmcloud/client_local.py
lmcloud/const.py
lmcloud/exceptions.py
lmcloud/helpers.py
lmcloud/lm_device.py
lmcloud/lm_grinder.py
lmcloud/lm_machine.py
lmcloud/models.py
lmcloud/py.typed
tests/__init__.py
tests/conftest.py
tests/test_grinder.py
tests/test_machine.py
lmcloud-1.2.3.dist-info/LICENSE
lmcloud-1.2.3.dist-info/METADATA
lmcloud-1.2.3.dist-info/WHEEL
lmcloud-1.2.3.dist-info/top_level.txt
lmcloud-1.2.3.dist-info/RECORD
