Metadata-Version: 2.1
Name: lmcloud
Version: 1.2.3
Summary: A Python implementation of the new La Marzocco API
Home-page: https://github.com/zweckj/lmcloud
Author: Josef Zweck
Author-email: 24647999+zweckj@users.noreply.github.com
License: MIT
Classifier: Development Status :: 3 - Alpha
Classifier: Intended Audience :: Developers
Classifier: Natural Language :: English
Classifier: License :: OSI Approved :: MIT License
Classifier: Programming Language :: Python
Classifier: Programming Language :: Python :: 3.12
Classifier: Programming Language :: Python :: Implementation :: CPython
License-File: LICENSE
Requires-Dist: httpx >=0.16.1
Requires-Dist: websockets >=11.0.2
Requires-Dist: bleak >=0.20.2
